simplePacking/app.py
simplePacking/example.py
simplePacking-1.0.1.dist-info/METADATA
simplePacking-1.0.1.dist-info/WHEEL
simplePacking-1.0.1.dist-info/top_level.txt
simplePacking-1.0.1.dist-info/RECORD
