Metadata-Version: 2.1
Name: simplePacking
Version: 1.0.1
Summary: Simple Python packing example, calling to flask service to execute
Author: Noy Sartori
License: MIT
Requires-Python: >=3.6
